./.gitignore
./.python-version
./PKG-INFO
./README.md
./__init__.py
./main.py
./models.py
./pyproject.toml
./remote_main.py
./test-pre-publish-simple.ps1
./uv.lock
demo_mcp_server-1.0.2.dist-info/METADATA
demo_mcp_server-1.0.2.dist-info/WHEEL
demo_mcp_server-1.0.2.dist-info/entry_points.txt
demo_mcp_server-1.0.2.dist-info/RECORD
