Metadata-Version: 2.4
Name: demo-mcp-server
Version: 1.0.2
Summary: MCP server providing math operations and OnceHub booking calendar integration
Project-URL: Homepage, https://github.com/nikhil1109/demo-mcp-server
Project-URL: Repository, https://github.com/nikhil1109/demo-mcp-server
Project-URL: Documentation, https://github.com/nikhil1109/demo-mcp-server#readme
Author-email: Nikhil <your.email@example.com>
License: MIT
Keywords: booking,calendar,math,mcp,oncehub,server
Classifier: Development Status :: 4 - Beta
Classifier: Environment :: Console
Classifier: Intended Audience :: Developers
Classifier: License :: OSI Approved :: MIT License
Classifier: Programming Language :: Python :: 3
Classifier: Programming Language :: Python :: 3.10
Classifier: Programming Language :: Python :: 3.11
Classifier: Programming Language :: Python :: 3.12
Classifier: Programming Language :: Python :: 3.13
Requires-Python: >=3.10
Requires-Dist: httpx>=0.27.0
Requires-Dist: mcp>=1.0.0
